doorway/__init__.py
doorway/_atomic.py
doorway/_colors.py
doorway/_ctx.py
doorway/_env_vars.py
doorway/_fmt.py
doorway/_hash.py
doorway/_inout.py
doorway/_modify_path.py
doorway/_shard.py
doorway/_stale.py
doorway/x/__init__.py
doorway/x/_proxy.py
doorway/x/_uri.py
tests/test_fmt.py
tests/test_hash.py
tests/test_uri.py
doorway-0.6.3.dist-info/METADATA
doorway-0.6.3.dist-info/WHEEL
doorway-0.6.3.dist-info/top_level.txt
doorway-0.6.3.dist-info/RECORD
