Metadata-Version: 2.2
Name: doorway
Version: 0.6.3
Summary: Essential utilities for working with files, directories, and data.
Author-email: Nathan Juraj Michlo <NathanJMichlo@gmail.com>
License: MIT License
Project-URL: Homepage, https://github.com/nmichlo/doorway
Classifier: License :: OSI Approved :: MIT License
Classifier: Operating System :: OS Independent
Classifier: Programming Language :: Python :: 3.9
Classifier: Programming Language :: Python :: 3.10
Classifier: Programming Language :: Python :: 3.11
Classifier: Programming Language :: Python :: 3.12
Classifier: Programming Language :: Python :: 3.13
Classifier: Intended Audience :: Science/Research
Requires-Python: >=3.9
Provides-Extra: dev
Requires-Dist: pre-commit<3,>=2; extra == "dev"
Provides-Extra: test
Requires-Dist: pytest>=7; extra == "test"
Requires-Dist: pytest-cov>=2; extra == "test"
Provides-Extra: extras
Requires-Dist: rfc3986>=1; extra == "extras"
Requires-Dist: requests; extra == "extras"
Requires-Dist: cachier; extra == "extras"
Requires-Dist: tqdm; extra == "extras"
Requires-Dist: beautifulsoup4; extra == "extras"
